arifos-53.2.9.data/data/spec/constitutional_floors.schema.json
arifos-53.2.9.dist-info/licenses/LICENSE
codebase/__init__.py
codebase/authority.py
codebase/bundle_store.py
codebase/bundles.py
codebase/constants.py
codebase/constitutional_floors.py
codebase/entropy_compressor.py
codebase/entropy_dump.py
codebase/exceptions.py
codebase/kernel.py
codebase/loop_manager.py
codebase/metabolism.py
codebase/state.py
codebase/zkpc.py
codebase/agi/__init__.py
codebase/agi/action.py
codebase/agi/agi_components.py
codebase/agi/atlas.py
codebase/agi/engine.py
codebase/agi/engine_hardened.py
codebase/agi/executor.py
codebase/agi/hierarchy.py
codebase/agi/kernel.py
codebase/agi/precision.py
codebase/agi/trinity_sync.py
codebase/agi/trinity_sync_hardened.py
codebase/apex/__init__.py
codebase/apex/demo_nine_paradox.py
codebase/apex/equilibrium_finder.py
codebase/apex/floor_checks.py
codebase/apex/kernel.py
codebase/apex/psi_kernel.py
codebase/apex/trinity_nine.py
codebase/apex/contracts/__init__.py
codebase/apex/contracts/apex_prime_output_v41.py
codebase/apex/governance/__init__.py
codebase/apex/governance/fag.py
codebase/apex/governance/ledger.py
codebase/apex/governance/ledger_cryptography.py
codebase/apex/governance/ledger_hashing.py
codebase/apex/governance/merkle.py
codebase/apex/governance/merkle_ledger.py
codebase/apex/governance/proof_of_governance.py
codebase/apex/governance/session_physics.py
codebase/apex/governance/sovereign_signature.py
codebase/apex/governance/vault_retrieval.py
codebase/apex/governance/zkpc_runtime.py
codebase/archive/agi/agi_components.py
codebase/archive/agi/engine.py
codebase/archive/agi/evidence.py
codebase/archive/agi/hardening.py
codebase/archive/agi/kernel.py
codebase/archive/agi/metrics.py
codebase/archive/agi/parallel.py
codebase/archive/agi/trinity_sync.py
codebase/archive/agi/stages/__init__.py
codebase/archive/agi/stages/reason.py
codebase/archive/agi/stages/sense.py
codebase/archive/agi/stages/think.py
codebase/archive/asi/asi_components_v2.py
arifos-53.2.9.dist-info/METADATA
arifos-53.2.9.dist-info/WHEEL
arifos-53.2.9.dist-info/entry_points.txt
arifos-53.2.9.dist-info/top_level.txt
arifos-53.2.9.dist-info/RECORD
