Metadata-Version: 2.4
Name: arifos
Version: 53.2.9
Summary: AAA MCP - The constitutional AI safety gateway. Prevents lies with 13 enforceable floors (F1-F13), TEACH principles, and live thermodynamic governance. Built on the Trinity architecture (AGI/ASI/APEX) with immutable VAULT999 ledger. MCP-compatible. Live metrics dashboard. AGPL-3.0. Available at https://arifos.arif-fazil.com/
Author-email: Muhammad Arif bin Fazil <arifbfazil@gmail.com>
Maintainer-email: Muhammad Arif bin Fazil <arifbfazil@gmail.com>
License-Expression: AGPL-3.0-only
Project-URL: Homepage, https://github.com/ariffazil/arifOS
Project-URL: Documentation, https://github.com/ariffazil/arifOS/blob/main/README.md
Project-URL: Repository, https://github.com/ariffazil/arifOS
Project-URL: Issues, https://github.com/ariffazil/arifOS/issues
Project-URL: Changelog, https://github.com/ariffazil/arifOS/blob/main/CHANGELOG.md
Project-URL: Live Server, https://arif-fazil.com/
Project-URL: Health Check, https://aaamcp.arif-fazil.com/health
Project-URL: MCP Endpoint, https://aaamcp.arif-fazil.com/mcp
Keywords: ai-governance,ai-safety,constitutional-ai,ai-filter,ai-guardrails,truth-detection,empathy,reversibility,clarity,humility,atlas-333,smart-routing,888-hold,crisis-detection,trinity-architecture,agi-asi-apex,tri-witness,mcp,mcp-server,model-context-protocol,chatgpt,claude,claude-desktop,cursor-ide,gemini,llm,hallucination-prevention,immutable-ledger,merkle-audit,thermodynamic-governance
Classifier: Development Status :: 4 - Beta
Classifier: Intended Audience :: Developers
Classifier: Intended Audience :: Science/Research
Classifier: Intended Audience :: Information Technology
Classifier: Operating System :: OS Independent
Classifier: Programming Language :: Python :: 3
Classifier: Programming Language :: Python :: 3.10
Classifier: Programming Language :: Python :: 3.11
Classifier: Programming Language :: Python :: 3.12
Classifier: Programming Language :: Python :: 3.13
Classifier: Topic :: Scientific/Engineering :: Artificial Intelligence
Classifier: Topic :: Software Development :: Libraries :: Python Modules
Classifier: Topic :: System :: Monitoring
Classifier: Topic :: Security
Classifier: Typing :: Typed
Requires-Python: >=3.10
License-File: LICENSE
Requires-Dist: numpy>=1.20.0
Requires-Dist: pydantic>=2.0.0
Requires-Dist: anyio>=4.0.0
Requires-Dist: starlette>=0.30.0
Requires-Dist: fastmcp>=0.1.0
Requires-Dist: fastapi>=0.104.1
Requires-Dist: uvicorn[standard]>=0.24.0
Requires-Dist: sse-starlette>=1.8.2
Requires-Dist: mcp>=1.0.0
Requires-Dist: httpx>=0.25.0
Requires-Dist: prometheus-client>=0.19.0
Requires-Dist: rich>=13.7.0
Provides-Extra: dev
Requires-Dist: pytest>=7.0.0; extra == "dev"
Requires-Dist: pytest-cov>=4.0.0; extra == "dev"
Requires-Dist: black>=23.0.0; extra == "dev"
Requires-Dist: ruff>=0.1.0; extra == "dev"
Requires-Dist: mypy>=1.0.0; extra == "dev"
Requires-Dist: httpx>=0.28.0; extra == "dev"
Requires-Dist: beautifulsoup4>=4.12.0; extra == "dev"
Provides-Extra: yaml
Requires-Dist: pyyaml>=6.0.0; extra == "yaml"
Provides-Extra: api
Requires-Dist: fastapi>=0.100.0; extra == "api"
Requires-Dist: uvicorn[standard]>=0.23.0; extra == "api"
Requires-Dist: python-multipart>=0.0.6; extra == "api"
Provides-Extra: litellm
Requires-Dist: litellm>=1.0.0; extra == "litellm"
Provides-Extra: governed
Requires-Dist: litellm>=1.0.0; extra == "governed"
Requires-Dist: httpx>=0.28.0; extra == "governed"
Requires-Dist: pygments>=2.16.0; extra == "governed"
Requires-Dist: openai>=1.6.0; extra == "governed"
Provides-Extra: all
Requires-Dist: pyyaml>=6.0.0; extra == "all"
Requires-Dist: fastapi>=0.100.0; extra == "all"
Requires-Dist: uvicorn[standard]>=0.23.0; extra == "all"
Requires-Dist: python-multipart>=0.0.6; extra == "all"
Requires-Dist: litellm>=1.0.0; extra == "all"
Requires-Dist: httpx>=0.28.0; extra == "all"
Requires-Dist: pygments>=2.16.0; extra == "all"
Requires-Dist: openai>=1.6.0; extra == "all"
Requires-Dist: mcp>=1.0.0; extra == "all"
Dynamic: license-file
